folderhash/__init__.py
folderhash/__main__.py
folderhash/cli.py
folderhash-1.0.1.dist-info/DESCRIPTION.rst
folderhash-1.0.1.dist-info/METADATA
folderhash-1.0.1.dist-info/RECORD
folderhash-1.0.1.dist-info/WHEEL
folderhash-1.0.1.dist-info/entry_points.txt
folderhash-1.0.1.dist-info/metadata.json
folderhash-1.0.1.dist-info/top_level.txt
