Metadata-Version: 2.0
Name: folderhash
Version: 1.0.1
Summary: Compare folder contents via hash.
Home-page: https://github.com/scolby33/folderhash
Author: Scott Colby
Author-email: scolby33@gmail.com
License: MIT License
Keywords: filesystem,diff,hash
Platform: UNKNOWN
Classifier: Development Status :: 5 - Production/Stable
Classifier: Environment :: Console
Classifier: Framework :: AsyncIO
Classifier: Intended Audience :: Developers
Classifier: Intended Audience :: End Users/Desktop
Classifier: License :: OSI Approved :: MIT License
Classifier: Operating System :: OS Independent
Classifier: Programming Language :: Python
Classifier: Programming Language :: Python :: 3.6
Classifier: Topic :: Utilities
Requires-Dist: curio
Requires-Dist: docopt
